[
  {
    "address": "San Jorge, N-45",
    "city": "Chillan",
    "country": "Chile",
    "id": 9,
    "image_url": "https://blogger.googleusercontent.com/img/b/R29vZ2xl/AVvXsEg7ZlAmo7tpgzbRveNDNiBhOOfJsYvOqYJ4oa3LThr4XtMTnRq0o2A9awp4u7tSghkeD4Rc3F2nkKaQ409E7dSkE2tJsE8Y7KZSd0CAMnLHputhO35NBpJraiLQhiXifcx5nIQX/w1200-h630-p-k-no-nu/bora+futbol.jpg",
    "name": "Polideportivo La Liga",
    "stars": 4.5
  },
  {
    "address": "Calle Flores Millán 1005",
    "city": "Chillan",
    "country": "Chile",
    "id": 10,
    "image_url": "",
    "name": "Complejo Quilamapu",
    "stars": 3.7
  },
  {
    "address": "Km 14, Camino Las Mariposas",
    "city": "Chillan",
    "country": "Chile",
    "id": 11,
    "image_url": "",
    "name": "Canchas Las Mariposas",
    "stars": 4.3
  }
]
